{"name":"Krůček po krůčku","slug":"krucek-po-krucku-filmova-hudba","author":"filmová hudba","note":"Z pohadky, tajemstvi stare bambitky","text":"[C] [G]\nKrůček po krůčku\n[Ami] [F]\ndo světa kráčím.\n[C] [G]\nSama a zvesela\n[Ami] [F]\nsvůj krámek tlačím.\n[C] [G]\nKrůček po krůčku,\n[Ami] [F]\nó můj ty světe\n[C] [G]\nhrníčky, talířky,\n[Ami] [F]\nprodám co chcete.\n\n[C] [G]\nKrůček po krůčku\n[Ami] [F]\ndo světa kráčím.\n[C] [G]\nSám a zvesela,\n[Ami] [F]\nsnad na to stačím.\n[C] [G]\nKrůček po krůčku,\n[Ami] [F]\nó můj ty světe,\n[C] [G]\nnejistý, ale odvážný,\n[Ami] [F]\njsem v každé větě.\n\n[C] [Ami]\nCo mě dnes potká?\n[C] [G]\nV budoucnost hledím.\n[C] [Ami]\nJsem zvědavá holka.\n[C] [G]\nA já kluk co neví!\n"}